{
    "name": "odyssey",
    "title": "Odyssey",
    "description": "The Odyssey role-playing system for FoundryVTT.",
    "version": "0.1.2",

    "compatibility": {
      "minimum": "10",
      "verified": "10"
    },
    "authors": [
      {
        "name": "William Mullen"
      }
    ],
    "esmodules": [],
    "styles": [],
    "packs": [],
    "languages": [
      {
        "lang": "en",
        "name": "English",
        "path": "lang/en.json"
      }
    ],
    "socket": true,
    "gridDistance": 5,
    "gridUnits": "ft",
    "primaryTokenAttribute": "attributes.harm",
    "secondaryTokenAttribute": null,
    "url": "https://github.com/wmullen/odyssey",
    "manifest": "https://raw.githubusercontent.com/wmullen/odyssey/main/system.json"
}
